[
  {
    "Nº": 1,
    "APELLIDOS Y NOMBRES": "PAJARES GASTULO ELVA ROSA",
    "DNI": "08036916",
    "CIP/NSA": "302127000",
    "IMPORTE": 10,
    "DESCONTADO": 10
  },
  {
    "Nº": 2,
    "APELLIDOS Y NOMBRES": "ORTIZ DE ORUE SEGURA WILMAN",
    "DNI": "05376043",
    "CIP/NSA": "305437300",
    "IMPORTE": 10,
    "DESCONTADO": 10
  },
  {
    "Nº": 3,
    "APELLIDOS Y NOMBRES": "RAMOS BANCES LUIS",
    "DNI": "09494809",
    "CIP/NSA": "304139500",
    "IMPORTE": 10,
    "DESCONTADO": 10
  },
  {
    "Nº": 4,
    "APELLIDOS Y NOMBRES": "RODRIGUEZ CORDERO GUILLERMO ANTONIO",
    "DNI": "09634053",
    "CIP/NSA": "302414800",
    "IMPORTE": 10,
    "DESCONTADO": 10
  },
  {
    "Nº": 5,
    "APELLIDOS Y NOMBRES": "PINEDO ALVA JULIO ESTANISLAO",
    "DNI": "09717619",
    "CIP/NSA": "302227700",
    "IMPORTE": 10,
    "DESCONTADO": 10
  },
  {
    "Nº": 6,
    "APELLIDOS Y NOMBRES": "ACUÑA SOTO CESAR",
    "DNI": "07332516",
    "CIP/NSA": "304598600",
    "IMPORTE": 10,
    "DESCONTADO": 10
  },
  {
    "Nº": 7,
    "APELLIDOS Y NOMBRES": "MACEDO GARCIA AMERICO",
    "DNI": "10731290",
    "CIP/NSA": "303782700",
    "IMPORTE": 10,
    "DESCONTADO": 10
  },
  {
    "Nº": 8,
    "APELLIDOS Y NOMBRES": "PEREZ LOZANO TOMAS TEOFILO",
    "DNI": "05362095",
    "CIP/NSA": "306183300",
    "IMPORTE": 10,
    "DESCONTADO": 10
  },
  {
    "Nº": 9,
    "APELLIDOS Y NOMBRES": "CANAZAS CRUZ VALENTIN MOISES",
    "DNI": "29542550",
    "CIP/NSA": "306088800",
    "IMPORTE": 10,
    "DESCONTADO": 10
  },
  {
    "Nº": 10,
    "APELLIDOS Y NOMBRES": "NAPURI MAGUIÑO RAUL AUGUSTO",
    "DNI": "08164225",
    "CIP/NSA": "305383000",
    "IMPORTE": 10,
    "DESCONTADO": 10
  },
  {
    "Nº": 11,
    "APELLIDOS Y NOMBRES": "MARCOS VILLANUEVA URBANO",
    "DNI": "43297587",
    "CIP/NSA": "306182500",
    "IMPORTE": 10,
    "DESCONTADO": 10
  },
  {
    "Nº": 12,
    "APELLIDOS Y NOMBRES": "CAMPOS ZAVALA MOISES NATIVIDAD",
    "DNI": "08654423",
    "CIP/NSA": "301099600",
    "IMPORTE": 10,
    "DESCONTADO": 10
  },
  {
    "Nº": 13,
    "APELLIDOS Y NOMBRES": "BARRAZA MORAN MANUEL",
    "DNI": "09879485",
    "CIP/NSA": "303091100",
    "IMPORTE": 10,
    "DESCONTADO": 10
  },
  {
    "Nº": 14,
    "APELLIDOS Y NOMBRES": "CRUZ QUISPE RAMON",
    "DNI": "06987529",
    "CIP/NSA": "304918300",
    "IMPORTE": 10,
    "DESCONTADO": 10
  },
  {
    "Nº": 15,
    "APELLIDOS Y NOMBRES": "TORRES VARGAS JOSE ARISTIDES",
    "DNI": "25664266",
    "CIP/NSA": "305810700",
    "IMPORTE": 10,
    "DESCONTADO": 10
  },
  {
    "Nº": 16,
    "APELLIDOS Y NOMBRES": "YAURI TORRES FRANZ JUAN",
    "DNI": "10687034",
    "CIP/NSA": "305928600",
    "IMPORTE": 10,
    "DESCONTADO": 10
  },
  {
    "Nº": 17,
    "APELLIDOS Y NOMBRES": "CHOZO VELIZ WILLIAM",
    "DNI": "10277035",
    "CIP/NSA": "303295700",
    "IMPORTE": 10,
    "DESCONTADO": 10
  },
  {
    "Nº": 18,
    "APELLIDOS Y NOMBRES": "PALOMINO CARMONA TEODOMIRO",
    "DNI": "08076003",
    "CIP/NSA": "306592800",
    "IMPORTE": 10,
    "DESCONTADO": 10
  },
  {
    "Nº": 19,
    "APELLIDOS Y NOMBRES": "RUMIN MISAGEL AGUSTIN",
    "DNI": "23923904",
    "CIP/NSA": "306609600",
    "IMPORTE": 10,
    "DESCONTADO": 10
  },
  {
    "Nº": 20,
    "APELLIDOS Y NOMBRES": "ABAD CAMPOS PEDRO ANGEL",
    "DNI": "08393603",
    "CIP/NSA": "302946800",
    "IMPORTE": 10,
    "DESCONTADO": 10
  },
  {
    "Nº": 21,
    "APELLIDOS Y NOMBRES": "VELASQUEZ HUMPIRI LUCIANO",
    "DNI": "40274419",
    "CIP/NSA": "305881600",
    "IMPORTE": 10,
    "DESCONTADO": 10
  },
  {
    "Nº": 22,
    "APELLIDOS Y NOMBRES": "QUEVEDO MINO JOSE PEDRO",
    "DNI": "06433749",
    "CIP/NSA": "304080100",
    "IMPORTE": 10,
    "DESCONTADO": 10
  },
  {
    "Nº": 23,
    "APELLIDOS Y NOMBRES": "RICALDI CAJAHUANCA DEMETRIO",
    "DNI": "10031033",
    "CIP/NSA": "302374500",
    "IMPORTE": 10,
    "DESCONTADO": 10
  },
  {
    "Nº": 24,
    "APELLIDOS Y NOMBRES": "GUARDAMINO RODRIGUEZ MAURO",
    "DNI": "08122820",
    "CIP/NSA": "305102100",
    "IMPORTE": 10,
    "DESCONTADO": 10
  },
  {
    "Nº": 25,
    "APELLIDOS Y NOMBRES": "TACUNA QUISPE BRAULIO",
    "DNI": "08051154",
    "CIP/NSA": "302645000",
    "IMPORTE": 10,
    "DESCONTADO": 10
  },
  {
    "Nº": 26,
    "APELLIDOS Y NOMBRES": "GINES ORIHUELA EUSEBIO",
    "DNI": "08122147",
    "CIP/NSA": "301585800",
    "IMPORTE": 10,
    "DESCONTADO": 10
  },
  {
    "Nº": 27,
    "APELLIDOS Y NOMBRES": "RICALDI CAJAHUANCA ANTONIO",
    "DNI": "41043414",
    "CIP/NSA": "304175100",
    "IMPORTE": 10,
    "DESCONTADO": 10
  },
  {
    "Nº": 28,
    "APELLIDOS Y NOMBRES": "RAMOS NEIRA JUAN CARLOS ANTONIO ALEJANDRO LUIS",
    "DNI": "10077744",
    "CIP/NSA": "304144100",
    "IMPORTE": 10,
    "DESCONTADO": 10
  },
  {
    "Nº": 29,
    "APELLIDOS Y NOMBRES": "APOMAYTA CUTIPA GIL JOSUE",
    "DNI": "09822854",
    "CIP/NSA": "304656700",
    "IMPORTE": 10,
    "DESCONTADO": 10
  },
  {
    "Nº": 30,
    "APELLIDOS Y NOMBRES": "DIAZ SALAZAR JUAN JORGE",
    "DNI": "09833852",
    "CIP/NSA": "303432100",
    "IMPORTE": 10,
    "DESCONTADO": 10
  },
  {
    "Nº": 31,
    "APELLIDOS Y NOMBRES": "DAVILA HERRERA NEMECIO",
    "DNI": "08145380",
    "CIP/NSA": "301330800",
    "IMPORTE": 10,
    "DESCONTADO": 10
  },
  {
    "Nº": 32,
    "APELLIDOS Y NOMBRES": "JULCA PISFIL CECILIO FERNANDO",
    "DNI": "40656756",
    "CIP/NSA": "303695200",
    "IMPORTE": 10,
    "DESCONTADO": 10
  },
  {
    "Nº": 33,
    "APELLIDOS Y NOMBRES": "CHUQUIHUANGA RIMAICUNA LUCIO",
    "DNI": "33655255",
    "CIP/NSA": "313733300",
    "IMPORTE": 10,
    "DESCONTADO": 10
  },
  {
    "Nº": 34,
    "APELLIDOS Y NOMBRES": "LEON MACHACA MOISES ERASMO",
    "DNI": "44416606",
    "CIP/NSA": "303726600",
    "IMPORTE": 10,
    "DESCONTADO": 10
  },
  {
    "Nº": 35,
    "APELLIDOS Y NOMBRES": "MAQUERA HUANACUNI TELESFORO",
    "DNI": "08112762",
    "CIP/NSA": "303816500",
    "IMPORTE": 10,
    "DESCONTADO": 10
  },
  {
    "Nº": 36,
    "APELLIDOS Y NOMBRES": "MORI SAGASTEGUI CARLOS ORLANDO",
    "DNI": "00366669",
    "CIP/NSA": "306114000",
    "IMPORTE": 10,
    "DESCONTADO": 10
  },
  {
    "Nº": 37,
    "APELLIDOS Y NOMBRES": "HURTADO BEJAR GUMERCINDO",
    "DNI": "06976538",
    "CIP/NSA": "315653200",
    "IMPORTE": 10,
    "DESCONTADO": 10
  },
  {
    "Nº": 38,
    "APELLIDOS Y NOMBRES": "SUAREZ LEON FELIX MANUEL",
    "DNI": "41467880",
    "CIP/NSA": "314392900",
    "IMPORTE": 10,
    "DESCONTADO": 10
  },
  {
    "Nº": 39,
    "APELLIDOS Y NOMBRES": "PEREZ ANCHITA GERMAN",
    "DNI": "09410208",
    "CIP/NSA": "302201300",
    "IMPORTE": 10,
    "DESCONTADO": 10
  },
  {
    "Nº": 40,
    "APELLIDOS Y NOMBRES": "PAREDES HUARCAYA JULIAN",
    "DNI": "40146480",
    "CIP/NSA": "304012700",
    "IMPORTE": 10,
    "DESCONTADO": 10
  },
  {
    "Nº": 41,
    "APELLIDOS Y NOMBRES": "ALLCCA LUQUE CAMILO",
    "DNI": "43443836",
    "CIP/NSA": "306148500",
    "IMPORTE": 10,
    "DESCONTADO": 10
  },
  {
    "Nº": 42,
    "APELLIDOS Y NOMBRES": "PEREZ MONTERO CARLOS ALBERTO",
    "DNI": "09561851",
    "CIP/NSA": "305510800",
    "IMPORTE": 10,
    "DESCONTADO": 10
  },
  {
    "Nº": 43,
    "APELLIDOS Y NOMBRES": "BERROSPI QUINTO SERGIO",
    "DNI": "08755429",
    "CIP/NSA": "303120900",
    "IMPORTE": 10,
    "DESCONTADO": 10
  },
  {
    "Nº": 44,
    "APELLIDOS Y NOMBRES": "CHIRE TICONA TOMAS AQUILINO",
    "DNI": "08395593",
    "CIP/NSA": "301229800",
    "IMPORTE": 10,
    "DESCONTADO": 10
  },
  {
    "Nº": 45,
    "APELLIDOS Y NOMBRES": "MOREYRA OROZCO JUAN LINO",
    "DNI": "09602470",
    "CIP/NSA": "305365200",
    "IMPORTE": 10,
    "DESCONTADO": 10
  },
  {
    "Nº": 46,
    "APELLIDOS Y NOMBRES": "PANTA CHULLE TOMAS",
    "DNI": "03888671",
    "CIP/NSA": "306613400",
    "IMPORTE": 10,
    "DESCONTADO": 10
  },
  {
    "Nº": 47,
    "APELLIDOS Y NOMBRES": "ORTIZ OCHOA FERNANDO",
    "DNI": "09692481",
    "CIP/NSA": "305438100",
    "IMPORTE": 10,
    "DESCONTADO": 10
  },
  {
    "Nº": 48,
    "APELLIDOS Y NOMBRES": "CHUMPITAZ CHUMPITAZ LUIS ANDRES",
    "DNI": "10324164",
    "CIP/NSA": "304875600",
    "IMPORTE": 10,
    "DESCONTADO": 10
  },
  {
    "Nº": 49,
    "APELLIDOS Y NOMBRES": "CASQUI CARDENAS JOSE FILOMENO",
    "DNI": "02628223",
    "CIP/NSA": "300031100",
    "IMPORTE": 10,
    "DESCONTADO": 10
  },
  {
    "Nº": 50,
    "APELLIDOS Y NOMBRES": "HUANCAHUARI MOQUILLAZA GERARDO FRANCISCO",
    "DNI": "08146892",
    "CIP/NSA": "300072900",
    "IMPORTE": 10,
    "DESCONTADO": 10
  },
  {
    "Nº": 51,
    "APELLIDOS Y NOMBRES": "NARRO MIRANDA ALFONSO ELPIDIO",
    "DNI": "08145835",
    "CIP/NSA": "302044400",
    "IMPORTE": 10,
    "DESCONTADO": 10
  },
  {
    "Nº": 52,
    "APELLIDOS Y NOMBRES": "FIGUEROA LEON BALTAZAR",
    "DNI": "08830856",
    "CIP/NSA": "306068300",
    "IMPORTE": 10,
    "DESCONTADO": 10
  },
  {
    "Nº": 53,
    "APELLIDOS Y NOMBRES": "TACANGA GONZALES RAFAEL",
    "DNI": "09592632",
    "CIP/NSA": "581576200",
    "IMPORTE": 10,
    "DESCONTADO": 10
  },
  {
    "Nº": 54,
    "APELLIDOS Y NOMBRES": "HIDALGO SUAREZ PEDRO CLEMENTE",
    "DNI": "08018185",
    "CIP/NSA": "300592500",
    "IMPORTE": 10,
    "DESCONTADO": 10
  },
  {
    "Nº": 55,
    "APELLIDOS Y NOMBRES": "AUCASIME NUÑEZ JULIO LEONIDAS",
    "DNI": "40270510",
    "CIP/NSA": "303063600",
    "IMPORTE": 10,
    "DESCONTADO": 10
  },
  {
    "Nº": 56,
    "APELLIDOS Y NOMBRES": "CALISAYA ENRIQUEZ ENRIQUE ALEJANDRO",
    "DNI": "42348621",
    "CIP/NSA": "304757100",
    "IMPORTE": 10,
    "DESCONTADO": 10
  },
  {
    "Nº": 57,
    "APELLIDOS Y NOMBRES": "MURRIETA SAAVEDRA MARCIAL",
    "DNI": "43400565",
    "CIP/NSA": "303915300",
    "IMPORTE": 10,
    "DESCONTADO": 10
  },
  {
    "Nº": 58,
    "APELLIDOS Y NOMBRES": "PELAYO FERNANDEZ LUCIANO MAXIMO",
    "DNI": "10723468",
    "CIP/NSA": "305491800",
    "IMPORTE": 10,
    "DESCONTADO": 10
  },
  {
    "Nº": 59,
    "APELLIDOS Y NOMBRES": "TSUCHIYA VASQUEZ SEGUNDO MARTINIANO",
    "DNI": "06118805",
    "CIP/NSA": "302711200",
    "IMPORTE": 10,
    "DESCONTADO": 10
  },
  {
    "Nº": 60,
    "APELLIDOS Y NOMBRES": "CHAVEZ MONTENEGRO ALFONSO",
    "DNI": "08751014",
    "CIP/NSA": "303274400",
    "IMPORTE": 10,
    "DESCONTADO": 10
  },
  {
    "Nº": 61,
    "APELLIDOS Y NOMBRES": "MAMANI SERPA FLORENCIO DANIEL",
    "DNI": "23814415",
    "CIP/NSA": "306611800",
    "IMPORTE": 10,
    "DESCONTADO": 10
  },
  {
    "Nº": 62,
    "APELLIDOS Y NOMBRES": "LOPEZ RODRIGUEZ ALFONSO",
    "DNI": "09829179",
    "CIP/NSA": "305239700",
    "IMPORTE": 10,
    "DESCONTADO": 10
  },
  {
    "Nº": 63,
    "APELLIDOS Y NOMBRES": "GUERRA CANAYO VIDAL",
    "DNI": "43650407",
    "CIP/NSA": "310038300",
    "IMPORTE": 10,
    "DESCONTADO": 10
  },
  {
    "Nº": 64,
    "APELLIDOS Y NOMBRES": "RIVAS GUZMAN ROSALIO",
    "DNI": "10229201",
    "CIP/NSA": "305630900",
    "IMPORTE": 10,
    "DESCONTADO": 10
  },
  {
    "Nº": 65,
    "APELLIDOS Y NOMBRES": "YAICURIMA MORI BERNAL",
    "DNI": "01082983",
    "CIP/NSA": "581258500",
    "IMPORTE": 10,
    "DESCONTADO": 10
  },
  {
    "Nº": 66,
    "APELLIDOS Y NOMBRES": "CHAVARRIA ROSAS ESTEBAN MAURO",
    "DNI": "09348017",
    "CIP/NSA": "301213100",
    "IMPORTE": 10,
    "DESCONTADO": 10
  },
  {
    "Nº": 67,
    "APELLIDOS Y NOMBRES": "DIAZ USHIÑAHUA ADAN SEGUNDO",
    "DNI": "09717291",
    "CIP/NSA": "301386300",
    "IMPORTE": 10,
    "DESCONTADO": 10
  },
  {
    "Nº": 68,
    "APELLIDOS Y NOMBRES": "LEON ALCANTARA PEDRO ORLANDO",
    "DNI": "08122198",
    "CIP/NSA": "300352300",
    "IMPORTE": 10,
    "DESCONTADO": 10
  },
  {
    "Nº": 69,
    "APELLIDOS Y NOMBRES": "GUTIERREZ MELENDEZ TEMISTOCLES",
    "DNI": "40064493",
    "CIP/NSA": "301659500",
    "IMPORTE": 10,
    "DESCONTADO": 10
  },
  {
    "Nº": 70,
    "APELLIDOS Y NOMBRES": "ZAVALA GARCIA ARBUEZ",
    "DNI": "08621790",
    "CIP/NSA": "300456200",
    "IMPORTE": 10,
    "DESCONTADO": 10
  },
  {
    "Nº": 71,
    "APELLIDOS Y NOMBRES": "TERRONES GUTIERREZ JORGE ALFREDO",
    "DNI": "09820616",
    "CIP/NSA": "304382700",
    "IMPORTE": 10,
    "DESCONTADO": 10
  },
  {
    "Nº": 72,
    "APELLIDOS Y NOMBRES": "SORIANO GALLOSO VALENTIN MOISES",
    "DNI": "10027089",
    "CIP/NSA": "302614000",
    "IMPORTE": 10,
    "DESCONTADO": 10
  },
  {
    "Nº": 73,
    "APELLIDOS Y NOMBRES": "ZAMALLOA ZURCA JULIAN",
    "DNI": "08878988",
    "CIP/NSA": "304556000",
    "IMPORTE": 10,
    "DESCONTADO": 10
  },
  {
    "Nº": 74,
    "APELLIDOS Y NOMBRES": "ARIAS GONZALES FELIX ROBERTO",
    "DNI": "09581394",
    "CIP/NSA": "300944000",
    "IMPORTE": 10,
    "DESCONTADO": 10
  },
  {
    "Nº": 75,
    "APELLIDOS Y NOMBRES": "TUEROS POLANCO JOSE SILVESTRE",
    "DNI": "10093622",
    "CIP/NSA": "305818200",
    "IMPORTE": 10,
    "DESCONTADO": 10
  },
  {
    "Nº": 76,
    "APELLIDOS Y NOMBRES": "ARAKAKI CHINEN LUIS",
    "DNI": "07474418",
    "CIP/NSA": "300011700",
    "IMPORTE": 10,
    "DESCONTADO": 10
  },
  {
    "Nº": 77,
    "APELLIDOS Y NOMBRES": "RIVERA ZUÑIGA GERMAN",
    "DNI": "15355730",
    "CIP/NSA": "304203000",
    "IMPORTE": 10,
    "DESCONTADO": 10
  },
  {
    "Nº": 78,
    "APELLIDOS Y NOMBRES": "RIVERA CUBAS NESTOR GUILLERMO",
    "DNI": "08191409",
    "CIP/NSA": "306077200",
    "IMPORTE": 10,
    "DESCONTADO": 10
  },
  {
    "Nº": 79,
    "APELLIDOS Y NOMBRES": "LAZO ALVARADO TERENCIO EFRAIN",
    "DNI": "40224352",
    "CIP/NSA": "301801600",
    "IMPORTE": 10,
    "DESCONTADO": 10
  },
  {
    "Nº": 80,
    "APELLIDOS Y NOMBRES": "LEIVA VILLANUEVA ALEJANDRO",
    "DNI": "40758976",
    "CIP/NSA": "305220600",
    "IMPORTE": 10,
    "DESCONTADO": 10
  },
  {
    "Nº": 81,
    "APELLIDOS Y NOMBRES": "VALDIVIA MONTOYA ANTONIO GREGORIO",
    "DNI": "42763179",
    "CIP/NSA": "305838700",
    "IMPORTE": 10,
    "DESCONTADO": 10
  },
  {
    "Nº": 82,
    "APELLIDOS Y NOMBRES": "OLAYA GUTIERREZ MANUEL SEGUNDO",
    "DNI": "08841181",
    "CIP/NSA": "300104000",
    "IMPORTE": 10,
    "DESCONTADO": 10
  },
  {
    "Nº": 83,
    "APELLIDOS Y NOMBRES": "PINEDO RODRIGUEZ MIGUEL",
    "DNI": "09855188",
    "CIP/NSA": "300115600",
    "IMPORTE": 10,
    "DESCONTADO": 10
  },
  {
    "Nº": 84,
    "APELLIDOS Y NOMBRES": "SANGAMA ALVIS JACK",
    "DNI": "44434574",
    "CIP/NSA": "585149100",
    "IMPORTE": 10,
    "DESCONTADO": 10
  },
  {
    "Nº": 85,
    "APELLIDOS Y NOMBRES": "CUBAS SILVA LUCIO EDGAR",
    "DNI": "08766126",
    "CIP/NSA": "306623100",
    "IMPORTE": 10,
    "DESCONTADO": 10
  },
  {
    "Nº": 86,
    "APELLIDOS Y NOMBRES": "ALVAREZ MAURICIO OCTAVIO",
    "DNI": "08113444",
    "CIP/NSA": "300882700",
    "IMPORTE": 10,
    "DESCONTADO": 10
  },
  {
    "Nº": 87,
    "APELLIDOS Y NOMBRES": "SANCHEZ CABANILLAS VICTOR",
    "DNI": "06668941",
    "CIP/NSA": "305721600",
    "IMPORTE": 10,
    "DESCONTADO": 10
  },
  {
    "Nº": 88,
    "APELLIDOS Y NOMBRES": "SOTO MENDIETA JAVIER",
    "DNI": "41417212",
    "CIP/NSA": "304351700",
    "IMPORTE": 10,
    "DESCONTADO": 10
  },
  {
    "Nº": 89,
    "APELLIDOS Y NOMBRES": "ZAVALA CRUZ MIGUEL ANGEL",
    "DNI": "09376092",
    "CIP/NSA": "304571400",
    "IMPORTE": 10,
    "DESCONTADO": 10
  },
  {
    "Nº": 90,
    "APELLIDOS Y NOMBRES": "MOSTACERO BACA OSCAR",
    "DNI": "09414673",
    "CIP/NSA": "300382500",
    "IMPORTE": 10,
    "DESCONTADO": 10
  },
  {
    "Nº": 91,
    "APELLIDOS Y NOMBRES": "VALDEZ CONTRERAS ISAAC LIZARDO",
    "DNI": "08647744",
    "CIP/NSA": "304434300",
    "IMPORTE": 10,
    "DESCONTADO": 10
  },
  {
    "Nº": 92,
    "APELLIDOS Y NOMBRES": "LOAIZA VILLAFUERTE LUIS BENEDICTO",
    "DNI": "08833117",
    "CIP/NSA": "302839900",
    "IMPORTE": 10,
    "DESCONTADO": 10
  },
  {
    "Nº": 93,
    "APELLIDOS Y NOMBRES": "HUAMAN SOCUALAYA FLORENCIO",
    "DNI": "08148206",
    "CIP/NSA": "303639100",
    "IMPORTE": 10,
    "DESCONTADO": 10
  },
  {
    "Nº": 94,
    "APELLIDOS Y NOMBRES": "QUISPE CAMPOS ISIDORO BUENAVENTURA",
    "DNI": "21542154",
    "CIP/NSA": "305558200",
    "IMPORTE": 10,
    "DESCONTADO": 10
  },
  {
    "Nº": 95,
    "APELLIDOS Y NOMBRES": "CAMACHO GARCIA FELIPE",
    "DNI": "43427402",
    "CIP/NSA": "304765200",
    "IMPORTE": 10,
    "DESCONTADO": 10
  },
  {
    "Nº": 96,
    "APELLIDOS Y NOMBRES": "CARLES TALLEDO JOSE",
    "DNI": "44103521",
    "CIP/NSA": "304793800",
    "IMPORTE": 10,
    "DESCONTADO": 10
  },
  {
    "Nº": 97,
    "APELLIDOS Y NOMBRES": "HUAMANI AVALOS JUAN ALBERTO",
    "DNI": "10078855",
    "CIP/NSA": "583648400",
    "IMPORTE": 10,
    "DESCONTADO": 10
  },
  {
    "Nº": 98,
    "APELLIDOS Y NOMBRES": "APARCANA CONTRERAS EFRAIN",
    "DNI": "41290033",
    "CIP/NSA": "303018000",
    "IMPORTE": 10,
    "DESCONTADO": 10
  },
  {
    "Nº": 99,
    "APELLIDOS Y NOMBRES": "GARCIA MEDINA MANUEL",
    "DNI": "42849276",
    "CIP/NSA": "305059900",
    "IMPORTE": 10,
    "DESCONTADO": 10
  },
  {
    "Nº": 100,
    "APELLIDOS Y NOMBRES": "DE LA CRUZ BALLASCO ANDRES ZOSIMO",
    "DNI": "05287898",
    "CIP/NSA": "304934500",
    "IMPORTE": 10,
    "DESCONTADO": 10
  },
  {
    "Nº": 101,
    "APELLIDOS Y NOMBRES": "AYALA ZAMORA RAUL",
    "DNI": "40615029",
    "CIP/NSA": "304690700",
    "IMPORTE": 10,
    "DESCONTADO": 10
  },
  {
    "Nº": 102,
    "APELLIDOS Y NOMBRES": "LEON FERNANDEZ JORGE JUAN",
    "DNI": "20016897",
    "CIP/NSA": "306616900",
    "IMPORTE": 10,
    "DESCONTADO": 10
  },
  {
    "Nº": 103,
    "APELLIDOS Y NOMBRES": "ALBURQUEQUE CHAVEZ NICOLAS",
    "DNI": "06990217",
    "CIP/NSA": "302978600",
    "IMPORTE": 10,
    "DESCONTADO": 10
  },
  {
    "Nº": 104,
    "APELLIDOS Y NOMBRES": "VELASQUEZ RAMOS CELSO ADOLFO",
    "DNI": "07825971",
    "CIP/NSA": "580822700",
    "IMPORTE": 10,
    "DESCONTADO": 10
  },
  {
    "Nº": 105,
    "APELLIDOS Y NOMBRES": "QUISPE POMATANTAS ZENON",
    "DNI": "43733020",
    "CIP/NSA": "305574400",
    "IMPORTE": 10,
    "DESCONTADO": 10
  },
  {
    "Nº": 106,
    "APELLIDOS Y NOMBRES": "ROSSELLO SALINAS MARCO ANTONIO",
    "DNI": "43808799",
    "CIP/NSA": "305684800",
    "IMPORTE": 10,
    "DESCONTADO": 10
  },
  {
    "Nº": 107,
    "APELLIDOS Y NOMBRES": "SANDOVAL JAVIER JULIO CESAR",
    "DNI": "06991513",
    "CIP/NSA": "305728300",
    "IMPORTE": 10,
    "DESCONTADO": 10
  },
  {
    "Nº": 108,
    "APELLIDOS Y NOMBRES": "MARCOS GOMEZ PEDRO PABLO",
    "DNI": "43587511",
    "CIP/NSA": "305284200",
    "IMPORTE": 10,
    "DESCONTADO": 10
  },
  {
    "Nº": 109,
    "APELLIDOS Y NOMBRES": "ENCALADA NUÑEZ LUIS DAGOBERTO",
    "DNI": "08114011",
    "CIP/NSA": "301409600",
    "IMPORTE": 10,
    "DESCONTADO": 10
  },
  {
    "Nº": 110,
    "APELLIDOS Y NOMBRES": "RODRIGUEZ ARENAS JUAN ISMAEL",
    "DNI": "09820519",
    "CIP/NSA": "302411300",
    "IMPORTE": 10,
    "DESCONTADO": 10
  },
  {
    "Nº": 111,
    "APELLIDOS Y NOMBRES": "IBARRA VILLANUEVA VICTOR",
    "DNI": "09822739",
    "CIP/NSA": "301741900",
    "IMPORTE": 10,
    "DESCONTADO": 10
  },
  {
    "Nº": 112,
    "APELLIDOS Y NOMBRES": "GASLA PADILLA DARWIN",
    "DNI": "06639888",
    "CIP/NSA": "301576900",
    "IMPORTE": 10,
    "DESCONTADO": 10
  },
  {
    "Nº": 113,
    "APELLIDOS Y NOMBRES": "SANCHEZ RIOS ALBERTO",
    "DNI": "42755492",
    "CIP/NSA": "304286300",
    "IMPORTE": 10,
    "DESCONTADO": 10
  },
  {
    "Nº": 114,
    "APELLIDOS Y NOMBRES": "FLOR QUISPE LUIS FILOMENO",
    "DNI": "42808764",
    "CIP/NSA": "305014900",
    "IMPORTE": 10,
    "DESCONTADO": 10
  },
  {
    "Nº": 115,
    "APELLIDOS Y NOMBRES": "VARGAS HUAMANI MACEDONIO",
    "DNI": "40129189",
    "CIP/NSA": "304452100",
    "IMPORTE": 10,
    "DESCONTADO": 10
  },
  {
    "Nº": 116,
    "APELLIDOS Y NOMBRES": "APARICIO MONTEAGUDO HERACLIO",
    "DNI": "08522631",
    "CIP/NSA": "300910600",
    "IMPORTE": 10,
    "DESCONTADO": 10
  },
  {
    "Nº": 117,
    "APELLIDOS Y NOMBRES": "GOMEZ ZEGARRA URBANO",
    "DNI": "08807157",
    "CIP/NSA": "301599800",
    "IMPORTE": 10,
    "DESCONTADO": 10
  },
  {
    "Nº": 118,
    "APELLIDOS Y NOMBRES": "SILVERIO ALVARADO VICTOR",
    "DNI": "08174280",
    "CIP/NSA": "304332000",
    "IMPORTE": 10,
    "DESCONTADO": 10
  },
  {
    "Nº": 119,
    "APELLIDOS Y NOMBRES": "HUAYHUA NINA VDA DE JIMENES PATRICIA EMILIANA",
    "DNI": "09583861",
    "CIP/NSA": "320546000",
    "IMPORTE": 10,
    "DESCONTADO": 10
  },
  {
    "Nº": 120,
    "APELLIDOS Y NOMBRES": "PILLPA ANTAY CARLOS ORLANDO",
    "DNI": "08952728",
    "CIP/NSA": null,
    "IMPORTE": 10,
    "DESCONTADO": 0
  }
]